{
    "chapter": "7.3",
    "name": "第三节 在实践中探索社会主义的发展规律",
    "actual_starting_page": "page0316.txt",
    "actual_ending_page": "page0323.txt",
    "mermaid_code": "mindmap\n\troot((第三节 在实践中探索社会主义的发展规律))\n\t\t民主与自我革命的重要性\n\t\t\t民主监督政府\n\t\t\t\t人民监督政府防止松懈\n\t\t\t\t人人负责避免人亡政息\n\t\t\t党的自我革命\n\t\t\t\t刮骨疗毒、壮士断腕的勇气\n\t\t\t\t自我净化、自我完善、自我革新、自我提高\n\t\t习近平新时代中国特色社会主义思想\n\t\t\t科学社会主义基本原则与当代中国实际结合\n\t\t\t\t全面建设社会主义现代化国家\n\t\t\t\t实现中华民族伟大复兴\n\t\t\t实践创新与理论创新良性互动\n\t\t\t引领和保障中国特色社会主义发展\n\t\t社会主义建设过程的长期性\n\t\t\t生产力发展状况制约\n\t\t\t\t大力发展生产力\n\t\t\t\t完成工业化和生产社会化任务\n\t\t\t经济基础和上层建筑发展状况制约\n\t\t\t\t建立和完善社会主义经济基础\n\t\t\t\t社会主义民主政治建设进程缓慢\n\t\t\t国际环境严峻挑战\n\t\t\t\t资本主义列强遏制和扼杀\n\t\t\t\t和平演变手段\n\t\t\t马克思主义执政党对社会主义道路探索\n\t\t\t\t长期探索和认识社会主义建设规律\n\t\t社会主义发展道路多样性\n\t\t\t各国国情差异\n\t\t\t\t生产力发展水平不同\n\t\t\t\t历史文化传统不同\n\t\t\t时代和实践不断发展\n\t\t\t\t适应时代要求调整发展道路\n\t\t探索适合本国国情的发展道路\n\t\t\t坚持对待马克思主义的科学态度\n\t\t\t从当时当地的历史条件出发\n\t\t\t充分吸收人类一切优秀文明成果\n\t\t社会主义在实践中开拓前进\n\t\t\t亿万人民群众的伟大实践\n\t\t\t不断探索的过程"
}